rpm_make_rules_dependency_lister/__init__.py
rpm_make_rules_dependency_lister/__main__.py
rpm_make_rules_dependency_lister/rpm_frontend.py
rpm_make_rules_dependency_lister-1.11.1.dist-info/DESCRIPTION.rst
rpm_make_rules_dependency_lister-1.11.1.dist-info/METADATA
rpm_make_rules_dependency_lister-1.11.1.dist-info/RECORD
rpm_make_rules_dependency_lister-1.11.1.dist-info/WHEEL
rpm_make_rules_dependency_lister-1.11.1.dist-info/entry_points.txt
rpm_make_rules_dependency_lister-1.11.1.dist-info/metadata.json
rpm_make_rules_dependency_lister-1.11.1.dist-info/top_level.txt
