Metadata-Version: 2.0
Name: rpm-make-rules-dependency-lister
Version: 1.11.1
Summary: Module for analyzing RPM dependencies and speedup RPM building process.
Home-page: https://github.com/f18m/rpm-make-rules-dependency-lister
Author: Francesco Montorsi
Author-email: francesco.montorsi@gmail.com
License: UNKNOWN
Download-URL: https://github.com/f18m/rpm-make-rules-dependency-lister/archive/v1.11.1.tar.gz
Keywords: RPM,GNU make,dependency
Platform: UNKNOWN
Classifier: Programming Language :: Python :: 3
Classifier: Development Status :: 5 - Production/Stable
Classifier: Intended Audience :: Developers
Classifier: License :: OSI Approved :: MIT License
Classifier: Operating System :: POSIX
Requires-Python: >=3
